[
  {
    "category": "電気製品販売店・自治体施設等",
    "prefecture": "滋賀県",
    "store_name": "（株）アヤハディオ大津店",
    "address": "滋賀県大津市におの浜１－１－３",
    "phone": "077-522-2223"
  },
  {
    "category": "電気製品販売店・自治体施設等",
    "prefecture": "滋賀県",
    "store_name": "マツダ電設（株）",
    "address": "滋賀県大津市一里山４－１５－１２",
    "phone": "077-526-5789"
  },
  {
    "category": "電気製品販売店・自治体施設等",
    "prefecture": "滋賀県",
    "store_name": "中塚電機商会",
    "address": "滋賀県大津市中庄１－１３－１２",
    "phone": "077-524-7314"
  },
  {
    "category": "電気製品販売店・自治体施設等",
    "prefecture": "滋賀県",
    "store_name": "（株）ヤマダデンキテックランド大津堅田店",
    "address": "滋賀県大津市今堅田３－８－１",
    "phone": "077-571-1770"
  },
  {
    "category": "電気製品販売店・自治体施設等",
    "prefecture": "滋賀県",
    "store_name": "（株）わに電化ハートフル営業部",
    "address": "滋賀県大津市和邇中浜３３２－１",
    "phone": "077-594-1951"
  },
  {
    "category": "電気製品販売店・自治体施設等",
    "prefecture": "滋賀県",
    "store_name": "（株）平和堂和迩店",
    "address": "滋賀県大津市和邇中浜４３２",
    "phone": "077-594-3111"
  },
  {
    "category": "電気製品販売店・自治体施設等",
    "prefecture": "滋賀県",
    "store_name": "小野電化（株）本店",
    "address": "滋賀県大津市坂本２－１２－３１",
    "phone": "077-578-2007"
  },
  {
    "category": "電気製品販売店・自治体施設等",
    "prefecture": "滋賀県",
    "store_name": "（株）平和堂坂本店",
    "address": "滋賀県大津市坂本７－２４－１",
    "phone": "077-578-3111"
  },
  {
    "category": "電気製品販売店・自治体施設等",
    "prefecture": "滋賀県",
    "store_name": "湖西電化（株）",
    "address": "滋賀県大津市坂本７－４－９",
    "phone": "077-578-4376"
  },
  {
    "category": "電気製品販売店・自治体施設等",
    "prefecture": "滋賀県",
    "store_name": "（株）ヤマダデンキテックランド坂本店",
    "address": "滋賀県大津市坂本７丁目２４－１平和堂坂本３Ｆ",
    "phone": "077-579-1591"
  },
  {
    "category": "電気製品販売店・自治体施設等",
    "prefecture": "滋賀県",
    "store_name": "（株）平和堂アルプラザ瀬田",
    "address": "滋賀県大津市月輪１－３－８",
    "phone": "077-543-3111"
  },
  {
    "category": "電気製品販売店・自治体施設等",
    "prefecture": "滋賀県",
    "store_name": "（株）エディオンちとせかたた店",
    "address": "滋賀県大津市本堅田３－１２－３６",
    "phone": "077-573-2221"
  },
  {
    "category": "電気製品販売店・自治体施設等",
    "prefecture": "滋賀県",
    "store_name": "上新電機（株）堅田アル・プラザ店",
    "address": "滋賀県大津市本堅田５－２０－１０アル・プラザ堅田３Ｆ",
    "phone": "077-574-3344"
  },
  {
    "category": "電気製品販売店・自治体施設等",
    "prefecture": "滋賀県",
    "store_name": "（株）平和堂アルプラザ堅田",
    "address": "滋賀県大津市本堅田５－２０－１０",
    "phone": "077-573-3111"
  },
  {
    "category": "電気製品販売店・自治体施設等",
    "prefecture": "滋賀県",
    "store_name": "（株）平和堂平和堂石山",
    "address": "滋賀県大津市松原町１３－１５",
    "phone": "077-531-2820"
  },
  {
    "category": "電気製品販売店・自治体施設等",
    "prefecture": "滋賀県",
    "store_name": "岩井電化",
    "address": "滋賀県守山市小島町１８５０",
    "phone": "077-583-3121"
  },
  {
    "category": "電気製品販売店・自治体施設等",
    "prefecture": "滋賀県",
    "store_name": "（株）平和堂アルプラザ守山",
    "address": "滋賀県守山市播磨田町１８５－１",
    "phone": "077-581-1800"
  },
  {
    "category": "電気製品販売店・自治体施設等",
    "prefecture": "滋賀県",
    "store_name": "（株）関西ケーズデンキケーズデンキ守山店",
    "address": "滋賀県守山市播磨田町２００－１",
    "phone": "077-514-2227"
  },
  {
    "category": "電気製品販売店・自治体施設等",
    "prefecture": "滋賀県",
    "store_name": "イマイラジオ家電品売場",
    "address": "滋賀県守山市洲本町１３５１－３",
    "phone": "077-585-1064"
  },
  {
    "category": "電気製品販売店・自治体施設等",
    "prefecture": "滋賀県",
    "store_name": "ロイヤルホームセンター守山店",
    "address": "滋賀県守山市矢島町１４９",
    "phone": "077-585-5531"
  },
  {
    "category": "電気製品販売店・自治体施設等",
    "prefecture": "滋賀県",
    "store_name": "上新電機（株）ハズイタウン守山店",
    "address": "滋賀県守山市金森町４８０－１",
    "phone": "077-582-0351"
  },
  {
    "category": "電気製品販売店・自治体施設等",
    "prefecture": "滋賀県",
    "store_name": "（株）アヤハディオ守山店",
    "address": "滋賀県守山市金森町５６７－１",
    "phone": "077-582-9411"
  },
  {
    "category": "電気製品販売店・自治体施設等",
    "prefecture": "滋賀県",
    "store_name": "（株）関西ケーズデンキケーズデンキ彦根店",
    "address": "滋賀県彦根市古沢町１０３－１",
    "phone": "0749-21-3288"
  },
  {
    "category": "電気製品販売店・自治体施設等",
    "prefecture": "滋賀県",
    "store_name": "（株）平和堂アルプラザ彦根",
    "address": "滋賀県彦根市大東町２－２８",
    "phone": "0749-24-4111"
  },
  {
    "category": "電気製品販売店・自治体施設等",
    "prefecture": "滋賀県",
    "store_name": "マエダデンキ",
    "address": "滋賀県彦根市幸町２",
    "phone": "0749-22-8331"
  },
  {
    "category": "電気製品販売店・自治体施設等",
    "prefecture": "滋賀県",
    "store_name": "（株）丸正",
    "address": "滋賀県彦根市後三条町４８２－１",
    "phone": "0749-22-2400"
  },
  {
    "category": "電気製品販売店・自治体施設等",
    "prefecture": "滋賀県",
    "store_name": "（株）アヤハディオ南彦根店",
    "address": "滋賀県彦根市戸賀町６０－１",
    "phone": "0749-26-2533"
  },
  {
    "category": "電気製品販売店・自治体施設等",
    "prefecture": "滋賀県",
    "store_name": "（株）平和堂日夏店",
    "address": "滋賀県彦根市日夏町字堀溝３７０３－１",
    "phone": "0749-25-3111"
  },
  {
    "category": "電気製品販売店・自治体施設等",
    "prefecture": "滋賀県",
    "store_name": "（株）平和堂ビバシティ平和堂",
    "address": "滋賀県彦根市竹ヶ鼻町４３－１",
    "phone": "0749-27-5555"
  },
  {
    "category": "電気製品販売店・自治体施設等",
    "prefecture": "滋賀県",
    "store_name": "（株）ヤマダデンキＹＡＭＡＤＡ　ｗｅｂ．ｃｏｍ彦根店",
    "address": "滋賀県彦根市里根町５５－１６",
    "phone": "0749-21-3931"
  },
  {
    "category": "電気製品販売店・自治体施設等",
    "prefecture": "滋賀県",
    "store_name": "上新電機（株）彦根店",
    "address": "滋賀県彦根市高宮町１６１３－３",
    "phone": "0749-23-5411"
  },
  {
    "category": "電気製品販売店・自治体施設等",
    "prefecture": "滋賀県",
    "store_name": "（株）平和堂愛知川店",
    "address": "滋賀県愛知郡愛荘町愛知川５８",
    "phone": "0749-42-6200"
  },
  {
    "category": "電気製品販売店・自治体施設等",
    "prefecture": "滋賀県",
    "store_name": "（株）関西ケーズデンキケーズデンキ八日市インター店",
    "address": "滋賀県東近江市中小路町７１０－１",
    "phone": "0748-20-3377"
  },
  {
    "category": "電気製品販売店・自治体施設等",
    "prefecture": "滋賀県",
    "store_name": "（株）平和堂アルプラザ八日市",
    "address": "滋賀県東近江市八日市浜野町３－１",
    "phone": "0748-24-1222"
  },
  {
    "category": "電気製品販売店・自治体施設等",
    "prefecture": "滋賀県",
    "store_name": "上新電機（株）東近江店",
    "address": "滋賀県東近江市宮荘町６５",
    "phone": "0748-48-5911"
  },
  {
    "category": "電気製品販売店・自治体施設等",
    "prefecture": "滋賀県",
    "store_name": "（株）アヤハディオ湖東店",
    "address": "滋賀県東近江市小田苅町２００３",
    "phone": "0749-45-0500"
  },
  {
    "category": "電気製品販売店・自治体施設等",
    "prefecture": "滋賀県",
    "store_name": "増田電気商会",
    "address": "滋賀県東近江市山上町２０９２－２",
    "phone": "0748-27-0523"
  },
  {
    "category": "電気製品販売店・自治体施設等",
    "prefecture": "滋賀県",
    "store_name": "ＤＣＭ（株）ＤＣＭ能登川店",
    "address": "滋賀県東近江市林町９１",
    "phone": "0748-43-6033"
  },
  {
    "category": "電気製品販売店・自治体施設等",
    "prefecture": "滋賀県",
    "store_name": "（株）ヤマダデンキテックランド東近江店",
    "address": "滋賀県東近江市青葉町３８５",
    "phone": "0748-36-1161"
  },
  {
    "category": "電気製品販売店・自治体施設等",
    "prefecture": "滋賀県",
    "store_name": "ホダカ（株）ホダカ栗東店",
    "address": "滋賀県栗東市出庭５３０－１",
    "phone": "077-554-8001"
  },
  {
    "category": "電気製品販売店・自治体施設等",
    "prefecture": "滋賀県",
    "store_name": "ハシモト電器",
    "address": "滋賀県栗東市安養寺８－７－３２",
    "phone": "077-552-4671"
  },
  {
    "category": "電気製品販売店・自治体施設等",
    "prefecture": "滋賀県",
    "store_name": "（株）関西ケーズデンキケーズデンキ草津栗東店",
    "address": "滋賀県栗東市小柿７－８－９",
    "phone": "077-554-3300"
  },
  {
    "category": "電気製品販売店・自治体施設等",
    "prefecture": "滋賀県",
    "store_name": "（株）アヤハディオ栗東店",
    "address": "滋賀県栗東市小柿８－１－１３",
    "phone": "077-552-2222"
  },
  {
    "category": "電気製品販売店・自治体施設等",
    "prefecture": "滋賀県",
    "store_name": "（株）ヤマダデンキテックランド草津栗東店",
    "address": "滋賀県栗東市小柿８－８－１４",
    "phone": "077-551-3200"
  },
  {
    "category": "電気製品販売店・自治体施設等",
    "prefecture": "滋賀県",
    "store_name": "サノデンカ",
    "address": "滋賀県栗東市川辺２３７－１",
    "phone": "077-552-3840"
  },
  {
    "category": "電気製品販売店・自治体施設等",
    "prefecture": "滋賀県",
    "store_name": "（株）平和堂アルプラザ栗東",
    "address": "滋賀県栗東市綣２－３－２２",
    "phone": "077-551-6300"
  },
  {
    "category": "電気製品販売店・自治体施設等",
    "prefecture": "滋賀県",
    "store_name": "湖南市役所　東庁舎",
    "address": "滋賀県湖南市中央１－１",
    "phone": "0748-71-2326"
  },
  {
    "category": "電気製品販売店・自治体施設等",
    "prefecture": "滋賀県",
    "store_name": "湖南市リサイクルプラザ",
    "address": "滋賀県湖南市岩根１３６",
    "phone": "0748-75-3933"
  },
  {
    "category": "電気製品販売店・自治体施設等",
    "prefecture": "滋賀県",
    "store_name": "湖南市役所　西庁舎",
    "address": "滋賀県湖南市石部中央１－１－１",
    "phone": "0748-77-7010"
  },
  {
    "category": "電気製品販売店・自治体施設等",
    "prefecture": "滋賀県",
    "store_name": "（株）平和堂石部店",
    "address": "滋賀県湖南市石部中央６－１－３１",
    "phone": "0748-77-5331"
  },
  {
    "category": "電気製品販売店・自治体施設等",
    "prefecture": "滋賀県",
    "store_name": "（有）野瀬電機商会",
    "address": "滋賀県犬上郡甲良町横関７３８－２",
    "phone": "0749-38-2103"
  },
  {
    "category": "電気製品販売店・自治体施設等",
    "prefecture": "滋賀県",
    "store_name": "（株）関西ケーズデンキケーズデンキ豊郷店",
    "address": "滋賀県犬上郡豊郷町沢１６０",
    "phone": "0749-35-0041"
  },
  {
    "category": "電気製品販売店・自治体施設等",
    "prefecture": "滋賀県",
    "store_name": "ウエニシ電化店",
    "address": "滋賀県甲賀市信楽町長野５１６－３",
    "phone": "0748-82-0352"
  },
  {
    "category": "電気製品販売店・自治体施設等",
    "prefecture": "滋賀県",
    "store_name": "ニシダ電化サービス",
    "address": "滋賀県甲賀市水口町北脇１４１８－７",
    "phone": "0748-62-1419"
  },
  {
    "category": "電気製品販売店・自治体施設等",
    "prefecture": "滋賀県",
    "store_name": "（株）ヤマダデンキテックランド水口店",
    "address": "滋賀県甲賀市水口町北脇１７２９－１",
    "phone": "0748-76-4100"
  },
  {
    "category": "電気製品販売店・自治体施設等",
    "prefecture": "滋賀県",
    "store_name": "（株）関西ケーズデンキケーズデンキ水口店",
    "address": "滋賀県甲賀市水口町北脇４２７",
    "phone": "0748-65-6011"
  },
  {
    "category": "電気製品販売店・自治体施設等",
    "prefecture": "滋賀県",
    "store_name": "上新電機（株）水口店",
    "address": "滋賀県甲賀市水口町北脇４４０",
    "phone": "0748-63-8061"
  },
  {
    "category": "電気製品販売店・自治体施設等",
    "prefecture": "滋賀県",
    "store_name": "（株）平和堂アルプラザ水口",
    "address": "滋賀県甲賀市水口町本綾野５６６－１",
    "phone": "0748-62-7101"
  },
  {
    "category": "電気製品販売店・自治体施設等",
    "prefecture": "滋賀県",
    "store_name": "（株）アヤハディオ水口店",
    "address": "滋賀県甲賀市水口町水口５５５５",
    "phone": "0748-62-7771"
  },
  {
    "category": "電気製品販売店・自治体施設等",
    "prefecture": "滋賀県",
    "store_name": "ＤＣＭ（株）ＤＣＭ甲賀店",
    "address": "滋賀県甲賀市甲南町竜法師３３８－３",
    "phone": "0748-86-1700"
  },
  {
    "category": "電気製品販売店・自治体施設等",
    "prefecture": "滋賀県",
    "store_name": "（有）よしかわでんき",
    "address": "滋賀県甲賀市甲賀町上野１３６１",
    "phone": "0748-88-2171"
  },
  {
    "category": "電気製品販売店・自治体施設等",
    "prefecture": "滋賀県",
    "store_name": "（有）カワバタ電機",
    "address": "滋賀県米原市長岡１７２９－１",
    "phone": "0749-55-0362"
  },
  {
    "category": "電気製品販売店・自治体施設等",
    "prefecture": "滋賀県",
    "store_name": "（有）ワタナベ電器",
    "address": "滋賀県草津市上笠２－１２－２０",
    "phone": "077-564-5758"
  },
  {
    "category": "電気製品販売店・自治体施設等",
    "prefecture": "滋賀県",
    "store_name": "（株）スガジ電器",
    "address": "滋賀県草津市大路１－１５－３５",
    "phone": "077-562-1348"
  },
  {
    "category": "電気製品販売店・自治体施設等",
    "prefecture": "滋賀県",
    "store_name": "（株）平和堂くさつ平和堂",
    "address": "滋賀県草津市大路１丁目１０－２７",
    "phone": "077-562-2755"
  },
  {
    "category": "電気製品販売店・自治体施設等",
    "prefecture": "滋賀県",
    "store_name": "上新電機（株）草津イオンモール店",
    "address": "滋賀県草津市新浜町３００イオンモール草津・モール棟１Ｆ",
    "phone": "077-569-4611"
  },
  {
    "category": "電気製品販売店・自治体施設等",
    "prefecture": "滋賀県",
    "store_name": "（株）関西ケーズデンキケーズデンキ草津南店",
    "address": "滋賀県草津市新浜町４０８",
    "phone": "077-569-4342"
  },
  {
    "category": "電気製品販売店・自治体施設等",
    "prefecture": "滋賀県",
    "store_name": "上新電機（株）草津店",
    "address": "滋賀県草津市木川町３８９",
    "phone": "077-565-4711"
  },
  {
    "category": "電気製品販売店・自治体施設等",
    "prefecture": "滋賀県",
    "store_name": "（有）さわだでんき",
    "address": "滋賀県草津市片岡町１８３－８",
    "phone": "077-568-0703"
  },
  {
    "category": "電気製品販売店・自治体施設等",
    "prefecture": "滋賀県",
    "store_name": "（株）アヤハディオ草津店",
    "address": "滋賀県草津市西渋川１－２３－１",
    "phone": "077-561-6555"
  },
  {
    "category": "電気製品販売店・自治体施設等",
    "prefecture": "滋賀県",
    "store_name": "（株）平和堂アルプラザ草津",
    "address": "滋賀県草津市西渋川１－２３－３０",
    "phone": "077-561-6200"
  },
  {
    "category": "電気製品販売店・自治体施設等",
    "prefecture": "滋賀県",
    "store_name": "（株）アヤハディオ追分店",
    "address": "滋賀県草津市追分南２－１１－１１",
    "phone": "077-596-3611"
  },
  {
    "category": "電気製品販売店・自治体施設等",
    "prefecture": "滋賀県",
    "store_name": "草津市草津市立クリーンセンター　環境経済部　資源循環推進課",
    "address": "滋賀県草津市馬場町１２００ー２５草津市立クリーン内",
    "phone": "077-562-6361"
  },
  {
    "category": "電気製品販売店・自治体施設等",
    "prefecture": "滋賀県",
    "store_name": "（株）平和堂篠原店",
    "address": "滋賀県近江八幡市上野町１－１",
    "phone": "0748-32-1555"
  },
  {
    "category": "電気製品販売店・自治体施設等",
    "prefecture": "滋賀県",
    "store_name": "みやがわデンキ",
    "address": "滋賀県近江八幡市中小森６３０",
    "phone": "0748-33-0166"
  },
  {
    "category": "電気製品販売店・自治体施設等",
    "prefecture": "滋賀県",
    "store_name": "（株）関西ケーズデンキケーズデンキ近江八幡店",
    "address": "滋賀県近江八幡市土田町１４００番１",
    "phone": "0748-34-6055"
  },
  {
    "category": "電気製品販売店・自治体施設等",
    "prefecture": "滋賀県",
    "store_name": "荒川音光堂",
    "address": "滋賀県近江八幡市安土町常楽寺５９７",
    "phone": "0748-46-2227"
  },
  {
    "category": "電気製品販売店・自治体施設等",
    "prefecture": "滋賀県",
    "store_name": "（株）平和堂アルプラザ近江八幡",
    "address": "滋賀県近江八幡市桜宮町２０２－１",
    "phone": "0748-31-2880"
  },
  {
    "category": "電気製品販売店・自治体施設等",
    "prefecture": "滋賀県",
    "store_name": "（株）アヤハディオ八幡西ノ庄店",
    "address": "滋賀県近江八幡市西庄町１２５１",
    "phone": "0748-33-2121"
  },
  {
    "category": "電気製品販売店・自治体施設等",
    "prefecture": "滋賀県",
    "store_name": "（有）中野電機商会",
    "address": "滋賀県近江八幡市音羽町５－１",
    "phone": "0748-33-2545"
  },
  {
    "category": "電気製品販売店・自治体施設等",
    "prefecture": "滋賀県",
    "store_name": "ＤＣＭ（株）ＤＣＭ近江八幡店",
    "address": "滋賀県近江八幡市鷹飼町２２３－１",
    "phone": "0748-38-8787"
  },
  {
    "category": "電気製品販売店・自治体施設等",
    "prefecture": "滋賀県",
    "store_name": "（株）ヤマダデンキテックランド近江店",
    "address": "滋賀県近江八幡市鷹飼町３５１番１",
    "phone": "0748-29-3911"
  },
  {
    "category": "電気製品販売店・自治体施設等",
    "prefecture": "滋賀県",
    "store_name": "（株）平和堂アルプラザ野洲",
    "address": "滋賀県野洲市小篠原１０００",
    "phone": "077-588-5500"
  },
  {
    "category": "電気製品販売店・自治体施設等",
    "prefecture": "滋賀県",
    "store_name": "（株）督永Ｔｏｋｕｎａｇａ　１Ｆ電池売場",
    "address": "滋賀県野洲市西河原４－２５７７",
    "phone": "077-589-2056"
  },
  {
    "category": "電気製品販売店・自治体施設等",
    "prefecture": "滋賀県",
    "store_name": "村田電光（株）",
    "address": "滋賀県野洲市野洲１５１３－１",
    "phone": "077-587-1700"
  },
  {
    "category": "電気製品販売店・自治体施設等",
    "prefecture": "滋賀県",
    "store_name": "（株）ヤマダデンキテックランド長浜店",
    "address": "滋賀県長浜市八幡中山町１０１",
    "phone": "0749-64-6333"
  },
  {
    "category": "電気製品販売店・自治体施設等",
    "prefecture": "滋賀県",
    "store_name": "上新電機（株）長浜店",
    "address": "滋賀県長浜市八幡中山町５５",
    "phone": "0749-62-9911"
  },
  {
    "category": "電気製品販売店・自治体施設等",
    "prefecture": "滋賀県",
    "store_name": "（株）アヤハディオ長浜店",
    "address": "滋賀県長浜市八幡東町１３１",
    "phone": "0749-63-8111"
  },
  {
    "category": "電気製品販売店・自治体施設等",
    "prefecture": "滋賀県",
    "store_name": "（株）関西ケーズデンキケーズデンキ長浜店",
    "address": "滋賀県長浜市十里町１",
    "phone": "0749-68-3855"
  },
  {
    "category": "電気製品販売店・自治体施設等",
    "prefecture": "滋賀県",
    "store_name": "（株）平和堂アルプラザ長浜",
    "address": "滋賀県長浜市小堀町４５０",
    "phone": "0749-65-7700"
  },
  {
    "category": "電気製品販売店・自治体施設等",
    "prefecture": "滋賀県",
    "store_name": "ＤＣＭ（株）ＤＣＭ長浜店",
    "address": "滋賀県長浜市川崎町字羽織町２２６－１",
    "phone": "0749-65-6481"
  },
  {
    "category": "電気製品販売店・自治体施設等",
    "prefecture": "滋賀県",
    "store_name": "（株）平和堂木之本店",
    "address": "滋賀県長浜市木之本町木之本字五位１５７０－４",
    "phone": "0749-82-3111"
  },
  {
    "category": "電気製品販売店・自治体施設等",
    "prefecture": "滋賀県",
    "store_name": "（有）鈴木すずきデンキ",
    "address": "滋賀県長浜市木之本町木之本１５６５",
    "phone": "0749-82-2110"
  },
  {
    "category": "電気製品販売店・自治体施設等",
    "prefecture": "滋賀県",
    "store_name": "上新電機（株）近江今津店",
    "address": "滋賀県高島市今津町今津１６８８平和堂今津店２Ｆ",
    "phone": "0740-22-2911"
  },
  {
    "category": "電気製品販売店・自治体施設等",
    "prefecture": "滋賀県",
    "store_name": "（株）関西ケーズデンキケーズデンキ今津店",
    "address": "滋賀県高島市今津町南新保５３０－１",
    "phone": "0740-22-8120"
  },
  {
    "category": "電気製品販売店・自治体施設等",
    "prefecture": "滋賀県",
    "store_name": "（株）平和堂今津店",
    "address": "滋賀県高島市今津町大字今津１６８８",
    "phone": "0740-22-6611"
  },
  {
    "category": "電気製品販売店・自治体施設等",
    "prefecture": "滋賀県",
    "store_name": "（株）アヤハディオ安曇川店",
    "address": "滋賀県高島市安曇川町西万木２０２",
    "phone": "0740-32-8090"
  },
  {
    "category": "電気製品販売店・自治体施設等",
    "prefecture": "滋賀県",
    "store_name": "（株）平和堂あどがわ店",
    "address": "滋賀県高島市安曇川町西万木５５",
    "phone": "0740-32-2411"
  },
  {
    "category": "電気製品販売店・自治体施設等",
    "prefecture": "滋賀県",
    "store_name": "（株）デンキーズ",
    "address": "滋賀県高島市新旭町新庄１４２６－１",
    "phone": "0740-25-2185"
  },
  {
    "category": "電気製品販売店・自治体施設等",
    "prefecture": "滋賀県",
    "store_name": "ヘイラク電器",
    "address": "滋賀県高島市新旭町新庄５５５－８",
    "phone": "0740-25-3404"
  }
]
