[
  {
    "category": "自転車販売店",
    "prefecture": "佐賀県",
    "store_name": "伊万里市二里コミュニティセンター",
    "address": "佐賀県伊万里市二里町大里乙３２１－３",
    "phone": "0955-23-3024"
  },
  {
    "category": "自転車販売店",
    "prefecture": "佐賀県",
    "store_name": "伊万里市南波多コミュニティセンター",
    "address": "佐賀県伊万里市南波多町井手野２６８５－１",
    "phone": "0955-24-2001"
  },
  {
    "category": "自転車販売店",
    "prefecture": "佐賀県",
    "store_name": "伊万里市大坪コミュニティセンター",
    "address": "佐賀県伊万里市大坪町甲２８６３－１",
    "phone": "0955-23-9898"
  },
  {
    "category": "自転車販売店",
    "prefecture": "佐賀県",
    "store_name": "伊万里市大川内コミュニティセンター",
    "address": "佐賀県伊万里市大川内町丙２４１０－１",
    "phone": "0955-23-2774"
  },
  {
    "category": "自転車販売店",
    "prefecture": "佐賀県",
    "store_name": "伊万里市大川コミュニティセンター",
    "address": "佐賀県伊万里市大川町大川野３３４０－１",
    "phone": "0955-29-2001"
  },
  {
    "category": "自転車販売店",
    "prefecture": "佐賀県",
    "store_name": "伊万里市山代コミュニティセンター",
    "address": "佐賀県伊万里市山代町久原２６９６－２",
    "phone": "0955-28-2001"
  },
  {
    "category": "自転車販売店",
    "prefecture": "佐賀県",
    "store_name": "伊万里市牧島コミュニティセンター",
    "address": "佐賀県伊万里市木須町５８３２－２",
    "phone": "0955-22-5783"
  },
  {
    "category": "自転車販売店",
    "prefecture": "佐賀県",
    "store_name": "伊万里市東山代コミュニティセンター",
    "address": "佐賀県伊万里市東山代町里１０５",
    "phone": "0955-28-0001"
  },
  {
    "category": "自転車販売店",
    "prefecture": "佐賀県",
    "store_name": "伊万里市伊万里コミュニティセンター",
    "address": "佐賀県伊万里市松島町３５０－４",
    "phone": "0955-23-9988"
  },
  {
    "category": "自転車販売店",
    "prefecture": "佐賀県",
    "store_name": "佐賀県西部広域環境組合さが西部クリーンセンター　管理棟",
    "address": "佐賀県伊万里市松浦町山形５０９２－４",
    "phone": "0955-26-2353"
  },
  {
    "category": "自転車販売店",
    "prefecture": "佐賀県",
    "store_name": "伊万里市松浦コミュニティセンター",
    "address": "佐賀県伊万里市松浦町山形５４９０－２",
    "phone": "0955-26-2001"
  },
  {
    "category": "自転車販売店",
    "prefecture": "佐賀県",
    "store_name": "伊万里市波多津コミュニティセンター",
    "address": "佐賀県伊万里市波多津町辻２９８９－５",
    "phone": "0955-25-0001"
  },
  {
    "category": "自転車販売店",
    "prefecture": "佐賀県",
    "store_name": "伊万里市市民交流部　環境政策課",
    "address": "佐賀県伊万里市立花町１３５５－１",
    "phone": "0955-23-2145"
  },
  {
    "category": "自転車販売店",
    "prefecture": "佐賀県",
    "store_name": "伊万里市立花コミュニティセンター",
    "address": "佐賀県伊万里市立花町１８９１－７９",
    "phone": "0955-20-4567"
  },
  {
    "category": "自転車販売店",
    "prefecture": "佐賀県",
    "store_name": "サイクルショップ　オオクボ",
    "address": "佐賀県伊万里市立花町３４４９－７",
    "phone": "0955-23-4012"
  },
  {
    "category": "自転車販売店",
    "prefecture": "佐賀県",
    "store_name": "（株）あさひサイクルベースあさひ佐賀店",
    "address": "佐賀県佐賀市本庄町袋２４６－１",
    "phone": "0952-27-7742"
  },
  {
    "category": "自転車販売店",
    "prefecture": "佐賀県",
    "store_name": "唐津市七山市民センター",
    "address": "佐賀県唐津市七山滝川１２５４",
    "phone": "0955-53-7173"
  },
  {
    "category": "自転車販売店",
    "prefecture": "佐賀県",
    "store_name": "唐津市清掃センター",
    "address": "佐賀県唐津市北波多岸山２３４－２",
    "phone": "0955-64-3106"
  },
  {
    "category": "自転車販売店",
    "prefecture": "佐賀県",
    "store_name": "唐津市北波多市民センター",
    "address": "佐賀県唐津市北波多徳須恵１０９７－４",
    "phone": "0955-53-7133"
  },
  {
    "category": "自転車販売店",
    "prefecture": "佐賀県",
    "store_name": "唐津市厳木市民センター",
    "address": "佐賀県唐津市厳木町厳木９９７",
    "phone": "0955-53-7113"
  },
  {
    "category": "自転車販売店",
    "prefecture": "佐賀県",
    "store_name": "唐津市呼子市民センター",
    "address": "佐賀県唐津市呼子町呼子１９９５－１",
    "phone": "0955-53-7163"
  },
  {
    "category": "自転車販売店",
    "prefecture": "佐賀県",
    "store_name": "（株）あさひサイクルベースあさひ唐津店",
    "address": "佐賀県唐津市和多田本村２－１９",
    "phone": "0955-65-8330"
  },
  {
    "category": "自転車販売店",
    "prefecture": "佐賀県",
    "store_name": "唐津市浜玉市民センター",
    "address": "佐賀県唐津市浜玉町浜崎１４４５－１",
    "phone": "0955-53-7103"
  },
  {
    "category": "自転車販売店",
    "prefecture": "佐賀県",
    "store_name": "唐津市相知市民センター",
    "address": "佐賀県唐津市相知町相知２０５５－１",
    "phone": "0955-53-7123"
  },
  {
    "category": "自転車販売店",
    "prefecture": "佐賀県",
    "store_name": "唐津市肥前市民センター",
    "address": "佐賀県唐津市肥前町入野甲１７０３",
    "phone": "0955-53-7143"
  },
  {
    "category": "自転車販売店",
    "prefecture": "佐賀県",
    "store_name": "唐津市市役所　生活環境対策課",
    "address": "佐賀県唐津市西城内１－１",
    "phone": "0955-72-9175"
  },
  {
    "category": "自転車販売店",
    "prefecture": "佐賀県",
    "store_name": "唐津市鎮西市民センター",
    "address": "佐賀県唐津市鎮西町名護屋１５３０",
    "phone": "0955-53-7153"
  },
  {
    "category": "自転車販売店",
    "prefecture": "佐賀県",
    "store_name": "小城市市役所",
    "address": "佐賀県小城市三日月町長神田２３１２－２",
    "phone": "0952-37-6102"
  },
  {
    "category": "自転車販売店",
    "prefecture": "佐賀県",
    "store_name": "小城市廃棄物中継センター",
    "address": "佐賀県小城市牛津町柿樋瀬１１７４－１",
    "phone": "0952-37-6145"
  },
  {
    "category": "自転車販売店",
    "prefecture": "佐賀県",
    "store_name": "玄海町役場　生活環境課",
    "address": "佐賀県東松浦郡玄海町大字諸浦３４８",
    "phone": "0955-52-2189"
  },
  {
    "category": "自転車販売店",
    "prefecture": "佐賀県",
    "store_name": "江北町役場　町民生活課",
    "address": "佐賀県杵島郡江北町大字山口１６５１－１",
    "phone": "0952-86-5617"
  },
  {
    "category": "自転車販売店",
    "prefecture": "佐賀県",
    "store_name": "白石町役場　生活環境課",
    "address": "佐賀県杵島郡白石町大字福田１２４７－１",
    "phone": "0952-84-7118"
  },
  {
    "category": "自転車販売店",
    "prefecture": "佐賀県",
    "store_name": "サイクルハウスみぞぐち",
    "address": "佐賀県杵島郡白石町福田２２４６－１",
    "phone": "0952-84-2040"
  },
  {
    "category": "自転車販売店",
    "prefecture": "佐賀県",
    "store_name": "武雄市北方公民館",
    "address": "佐賀県武雄市北方町大字大崎２２１７",
    "phone": "0954-36-2515"
  },
  {
    "category": "自転車販売店",
    "prefecture": "佐賀県",
    "store_name": "武雄市山内公民館",
    "address": "佐賀県武雄市山内町大字三間板甲１３８００",
    "phone": "0954-45-2139"
  },
  {
    "category": "自転車販売店",
    "prefecture": "佐賀県",
    "store_name": "武雄市朝日公民館",
    "address": "佐賀県武雄市朝日町大字甘久４２９５",
    "phone": "0954-22-3872"
  },
  {
    "category": "自転車販売店",
    "prefecture": "佐賀県",
    "store_name": "武雄市東川登公民館",
    "address": "佐賀県武雄市東川登町大字永野６２４０－８",
    "phone": "0954-23-3009"
  },
  {
    "category": "自転車販売店",
    "prefecture": "佐賀県",
    "store_name": "武雄市橘公民館",
    "address": "佐賀県武雄市橘町大字大日８５０７－７",
    "phone": "0954-22-3884"
  },
  {
    "category": "自転車販売店",
    "prefecture": "佐賀県",
    "store_name": "武雄市武内公民館",
    "address": "佐賀県武雄市武内町大字真手野２８０４４",
    "phone": "0954-27-2001"
  },
  {
    "category": "自転車販売店",
    "prefecture": "佐賀県",
    "store_name": "武雄市環境部　環境課",
    "address": "佐賀県武雄市武雄町大字昭和１２－１０",
    "phone": "0954-27-7163"
  },
  {
    "category": "自転車販売店",
    "prefecture": "佐賀県",
    "store_name": "武雄市武雄公民館",
    "address": "佐賀県武雄市武雄町大字武雄５５３８－１",
    "phone": "0954-23-8147"
  },
  {
    "category": "自転車販売店",
    "prefecture": "佐賀県",
    "store_name": "武雄市若木公民館",
    "address": "佐賀県武雄市若木町大字川古７４７４",
    "phone": "0954-26-2004"
  },
  {
    "category": "自転車販売店",
    "prefecture": "佐賀県",
    "store_name": "武雄市西川登公民館",
    "address": "佐賀県武雄市西川登町大字神六２０１１４－４",
    "phone": "0954-28-2004"
  },
  {
    "category": "自転車販売店",
    "prefecture": "佐賀県",
    "store_name": "脊振共同塵芥処理組合",
    "address": "佐賀県神埼市脊振町鹿路３３６２脊振広域クリーンセンター",
    "phone": "0952-51-9010"
  },
  {
    "category": "自転車販売店",
    "prefecture": "佐賀県",
    "store_name": "有田町リサイクルプラザ",
    "address": "佐賀県西松浦郡有田町戸矢乙１５７４",
    "phone": "0955-41-1153"
  },
  {
    "category": "自転車販売店",
    "prefecture": "佐賀県",
    "store_name": "有田町役場",
    "address": "佐賀県西松浦郡有田町立部乙２２０２",
    "phone": "0955-46-2734"
  },
  {
    "category": "自転車販売店",
    "prefecture": "佐賀県",
    "store_name": "鹿島市ゼロカーボンシティ推進課",
    "address": "佐賀県鹿島市大字納富分２６４３－１",
    "phone": "0954-63-3416"
  }
]
